bigquery_agent/__init__.py
bigquery_agent/bigquery_helper.py
adkbq-0.1.0.dist-info/METADATA
adkbq-0.1.0.dist-info/WHEEL
adkbq-0.1.0.dist-info/top_level.txt
adkbq-0.1.0.dist-info/RECORD
